{
  "is": "system",
  "title": "Director",
  "permalink": "https://status.tjhsst.edu/affected/director/",
  "status": "disrupted", 
  "pages": [
      {
        "is": "issue",
        "title": "Director Web Management Interface Down",
        "createdAt": "2022-11-15 12:00:00 -0500 -0500",
        "lastMod": "2022-11-15 15:39:45 -0500 -0500",
        "permalink": "https://status.tjhsst.edu/issues/2022-11-15-director-interface/",
        "severity": "disrupted",
        "resolved": false,
        "informational": false,
        "resolvedAt": "<no value>",
        "affected": ["Director"],
        "filename": "2022-11-15-director-interface.md"
      }
    ,
      {
        "is": "issue",
        "title": "Director Files Not Loading",
        "createdAt": "2022-08-24 18:20:00 -0400 -0400",
        "lastMod": "2022-08-29 16:03:32 -0400 -0400",
        "permalink": "https://status.tjhsst.edu/issues/2022-08-24-director-files/",
        "severity": "disrupted",
        "resolved": true,
        "informational": false,
        "resolvedAt": "2022-08-29T15:35:51-04:00",
        "affected": ["Director"],
        "filename": "2022-08-24-director-files.md"
      }
    ,
      {
        "is": "issue",
        "title": "Web Services Down",
        "createdAt": "2022-05-22 05:32:40 -0400 -0400",
        "lastMod": "2022-05-28 15:52:36 -0400 -0400",
        "permalink": "https://status.tjhsst.edu/issues/2022-05-22-systems-down/",
        "severity": "down",
        "resolved": true,
        "informational": false,
        "resolvedAt": "2022-05-27T21:54:00-04:00",
        "affected": ["AI Grader", "Director", "DNS", "JupyterHub", "Ion", "Matterless", "Othello", "Signage", "Tin", "Webmail"],
        "filename": "2022-05-22-systems-down.md"
      }
    
  ]
}





